odoo/addons/pos_product_sort/README.rst
odoo/addons/pos_product_sort/__init__.py
odoo/addons/pos_product_sort/__manifest__.py
odoo/addons/pos_product_sort/i18n/fr.po
odoo/addons/pos_product_sort/i18n/pos_product_sort.pot
odoo/addons/pos_product_sort/readme/CONTRIBUTORS.rst
odoo/addons/pos_product_sort/readme/CREDITS.rst
odoo/addons/pos_product_sort/readme/DESCRIPTION.rst
odoo/addons/pos_product_sort/readme/ROADMAP.rst
odoo/addons/pos_product_sort/static/description/icon.png
odoo/addons/pos_product_sort/static/description/index.html
odoo/addons/pos_product_sort/static/description/point_of_sale_name_order.png
odoo/addons/pos_product_sort/static/description/point_of_sale_sequence_order.png
odoo/addons/pos_product_sort/static/src/js/models.js
odoo/addons/pos_product_sort/views/assets.xml
odoo13_addon_pos_product_sort-13.0.1.0.1.dist-info/METADATA
odoo13_addon_pos_product_sort-13.0.1.0.1.dist-info/WHEEL
odoo13_addon_pos_product_sort-13.0.1.0.1.dist-info/top_level.txt
odoo13_addon_pos_product_sort-13.0.1.0.1.dist-info/RECORD
